[{"lat": "23.5833", "lon": "119.433", "value": "5", "type": "ferry"}, 
{"lat": "23.683300000000003", "lon": "119.533", "value": "1", "type": "ship"}, 
{"lat": "23.683300000000003", "lon": "119.33300000000001", "value": "3", "type": "ferry"}, 
{"lat": "23.4833", "lon": "119.533", "value": "1", "type": "ship"}, 
{"lat": "23.4833", "lon": "119.33300000000001", "value": "4", "type": "ferry"}, 
{"lat": "23.59", "lon": "119.9533", "value": "0", "type": "uuv"}, 
{"lat": "23.69", "lon": "120.0533", "value": "0", "type": "uuv"}, 
{"lat": "23.69", "lon": "119.8533", "value": "0", "type": "usv"}, 
{"lat": "23.49", "lon": "120.0533", "value": "0", "type": "usv"}, 
{"lat": "23.49", "lon": "119.8533", "value": "0", "type": "uav"}, 
{"lat": "23.39", "lon": "119.9533", "value": "0", "type": "uav"}]